youtube_transcript_cli/__init__.py
youtube_transcript_cli/cli.py
youtube_transcript_cli-0.1.0.dist-info/LICENSE
youtube_transcript_cli-0.1.0.dist-info/METADATA
youtube_transcript_cli-0.1.0.dist-info/WHEEL
youtube_transcript_cli-0.1.0.dist-info/entry_points.txt
youtube_transcript_cli-0.1.0.dist-info/top_level.txt
youtube_transcript_cli-0.1.0.dist-info/RECORD
