Metadata-Version: 2.1
Name: youtube-transcript-cli
Version: 0.1.0
Summary: A CLI tool to fetch and display YouTube video transcripts.
Author: NickMystic
License: MIT License
Requires-Python: >=3.6
License-File: LICENSE
Requires-Dist: youtube-transcript-api>=0.6.2
